mlintern010/__init__.py
mlintern010/main.py
mlintern010-0.1.5.dist-info/LICENSE
mlintern010-0.1.5.dist-info/METADATA
mlintern010-0.1.5.dist-info/WHEEL
mlintern010-0.1.5.dist-info/entry_points.txt
mlintern010-0.1.5.dist-info/top_level.txt
mlintern010-0.1.5.dist-info/RECORD
