Metadata-Version: 2.1
Name: mlintern010
Version: 0.1.5
License-File: LICENSE
Requires-Dist: numpy
Requires-Dist: pandas
Requires-Dist: termcolor
